pysapbydesign/Sapbydesign.py
pysapbydesign/__init__.py
pysapbydesign/auth.py
pysapbydesign-0.0.1.dist-info/LICENSE
pysapbydesign-0.0.1.dist-info/METADATA
pysapbydesign-0.0.1.dist-info/WHEEL
pysapbydesign-0.0.1.dist-info/top_level.txt
pysapbydesign-0.0.1.dist-info/RECORD
