Metadata-Version: 2.1
Name: pysapbydesign
Version: 0.0.1
Summary: A SAP By Design connector
Home-page: https://github.com/dacker-team/pysapbydesign
Author: Dacker
Author-email: hello@dacker.co
License: UNKNOWN
Platform: UNKNOWN
Classifier: Programming Language :: Python :: 3
Classifier: License :: OSI Approved :: MIT License
Classifier: Operating System :: OS Independent
Requires-Python: >=3
Requires-Dist: dbstream (>=0.0.16)
